LICENSE
MANIFEST.in
README.md
requirements.txt
setup.py
discopop.egg-info/PKG-INFO
discopop.egg-info/SOURCES.txt
discopop.egg-info/dependency_links.txt
discopop.egg-info/entry_points.txt
discopop.egg-info/requires.txt
discopop.egg-info/top_level.txt
discopop.egg-info/zip-safe
discopop_explorer/__init__.py
discopop_explorer/__main__.py
discopop_explorer/discopop_explorer.py
discopop_explorer/json_serializer.py
discopop_explorer/parallel_utils.py
discopop_explorer/pattern_detection.py
discopop_explorer/utils.py
discopop_explorer/aliases/LineID.py
discopop_explorer/aliases/MemoryRegion.py
discopop_explorer/aliases/NodeID.py
discopop_explorer/aliases/__init__.py
discopop_explorer/classes/__init__.py
discopop_explorer/classes/variable.py
discopop_explorer/classes/PEGraph/CUNode.py
discopop_explorer/classes/PEGraph/Dependency.py
discopop_explorer/classes/PEGraph/DummyNode.py
discopop_explorer/classes/PEGraph/FunctionNode.py
discopop_explorer/classes/PEGraph/LoopNode.py
discopop_explorer/classes/PEGraph/Node.py
discopop_explorer/classes/PEGraph/NodeT.py
discopop_explorer/classes/PEGraph/PEGraphX.py
discopop_explorer/classes/PEGraph/__init__.py
discopop_explorer/classes/patterns/PatternBase.py
discopop_explorer/classes/patterns/PatternInfo.py
discopop_explorer/classes/patterns/__init__.py
discopop_explorer/enums/DepType.py
discopop_explorer/enums/EdgeType.py
discopop_explorer/enums/MWType.py
discopop_explorer/enums/NodeType.py
discopop_explorer/enums/__init__.py
discopop_explorer/functions/__init__.py
discopop_explorer/functions/PEGraph/__init__.py
discopop_explorer/functions/PEGraph/output/__init__.py
discopop_explorer/functions/PEGraph/output/gephi.py
discopop_explorer/functions/PEGraph/output/json.py
discopop_explorer/functions/PEGraph/properties/__init__.py
discopop_explorer/functions/PEGraph/properties/check_reachability.py
discopop_explorer/functions/PEGraph/properties/depends_ignore_readonly.py
discopop_explorer/functions/PEGraph/properties/is_loop_index.py
discopop_explorer/functions/PEGraph/properties/is_passed_by_reference.py
discopop_explorer/functions/PEGraph/properties/is_predecessor.py
discopop_explorer/functions/PEGraph/properties/is_readonly_inside_loop_body.py
