Metadata-Version: 2.1
Name: discopop
Version: 5.0.1
Summary: DiscoPoP is a tool that helps software developers parallelize their programs with threads. It discovers potential parallelism in a sequential program and makes recommendations on how to exploit it.
Home-page: https://www.discopop.tu-darmstadt.de/
Author: TU Darmstadt and Iowa State University
Author-email: discopop@lists.parallel.informatik.tu-darmstadt.de
License: UNKNOWN
Platform: UNKNOWN
Classifier: Development Status :: 4 - Beta
Classifier: Environment :: Console
Classifier: Intended Audience :: Developers
Classifier: License :: OSI Approved :: BSD License
Classifier: Operating System :: OS Independent
Classifier: Programming Language :: Python :: 3
Classifier: Topic :: Software Development
Requires-Python: >=3.6
Provides-Extra: dev
Provides-Extra: ci
